codepacker/GUI.py
codepacker/__init__.py
codepacker/codeServices.py
codepacker/core.py
codepacker/tests.py
codepacker/utils.py
codepacker-12.6.0.dist-info/METADATA
codepacker-12.6.0.dist-info/WHEEL
codepacker-12.6.0.dist-info/entry_points.txt
codepacker-12.6.0.dist-info/top_level.txt
codepacker-12.6.0.dist-info/RECORD
