Metadata-Version: 2.4
Name: codepacker
Version: 12.6.0
Summary: Enhanced Updates.
Author: BMI-MoonspicAI
